LICENSE
NOTICE
README.md
datapane/__init__.py
datapane/_vendor/base64io/LICENSE
datapane/_vendor/base64io/__init__.py
datapane/_vendor/bottle.LICENSE
datapane/_vendor/bottle.py
datapane/_vendor/munch/LICENSE
datapane/_vendor/munch/LICENSE.txt
datapane/_vendor/munch/__init__.py
datapane/_vendor/munch/python3_compat.py
datapane/_version.py
datapane/app/__init__.py
datapane/app/hosting_utils.py
datapane/app/json_rpc.py
datapane/app/plugins.py
datapane/app/runtime.py
datapane/app/server.py
datapane/blocks/__init__.py
datapane/blocks/asset.py
datapane/blocks/base.py
datapane/blocks/compute.py
datapane/blocks/layout.py
datapane/blocks/misc_blocks.py
datapane/blocks/parameters.py
datapane/blocks/text.py
datapane/blocks/wrappers.py
datapane/builtins.py
datapane/client/__init__.py
datapane/client/__main__.py
datapane/client/analytics.py
datapane/client/commands.py
datapane/client/config.py
datapane/client/exceptions.py
datapane/client/utils.py
datapane/cloud_api/__init__.py
datapane/cloud_api/common.py
datapane/cloud_api/dp_object.py
datapane/cloud_api/file.py
datapane/cloud_api/report.py
datapane/cloud_api/user.py
datapane/common/__init__.py
datapane/common/datafiles.py
datapane/common/df_processor.py
datapane/common/dp_types.py
datapane/common/ops_utils.py
datapane/common/utils.py
datapane/common/versioning.py
datapane/common/viewxml_utils.py
datapane/ipython/__init__.py
datapane/ipython/environment.py
datapane/ipython/exceptions.py
datapane/ipython/templates.py
datapane/ipython/utils.py
datapane/legacy_apps/__init__.py
datapane/legacy_apps/builder.py
datapane/legacy_apps/config.py
datapane/legacy_runner/__init__.py
datapane/legacy_runner/__main__.py
datapane/legacy_runner/config.py
datapane/legacy_runner/exceptions.py
datapane/legacy_runner/exec_script.py
datapane/legacy_runner/typedefs.py
datapane/optional_libs.py
datapane/processors/__init__.py
datapane/processors/api.py
datapane/processors/file_store.py
datapane/processors/processors.py
datapane/processors/types.py
datapane-0.16.7.dist-info/LICENSE
datapane-0.16.7.dist-info/METADATA
datapane-0.16.7.dist-info/WHEEL
datapane-0.16.7.dist-info/entry_points.txt
datapane-0.16.7.dist-info/RECORD
