Metadata-Version: 2.1
Name: datapane
Version: 0.16.7
Summary: Datapane client library and CLI tool
Home-page: https://www.datapane.com
License: Apache-2.0
Keywords: data,analysis,jupyter,pandas,altair
Author: Datapane Team
Author-email: dev@datapane.com
Requires-Python: >=3.8.0,<4.0.0
Classifier: Development Status :: 2 - Pre-Alpha
Classifier: Environment :: Console
Classifier: Intended Audience :: Developers
Classifier: License :: OSI Approved :: Apache Software License
Classifier: Natural Language :: English
Classifier: Operating System :: OS Independent
Classifier: Programming Language :: Python :: 3
Classifier: Programming Language :: Python :: 3.8
Classifier: Programming Language :: Python :: 3.9
Classifier: Programming Language :: Python :: 3.10
Classifier: Programming Language :: Python :: 3.11
Classifier: Topic :: Software Development
Classifier: Topic :: Software Development :: Libraries :: Python Modules
Provides-Extra: cloud
Provides-Extra: plotting
Requires-Dist: PyYAML (>=5.4.0,<7.0.0)
Requires-Dist: altair (>=4.0.0,<5.0.0)
Requires-Dist: bokeh (>=2.3.0,<3.0.0) ; extra == "plotting"
Requires-Dist: boltons (>=20.0.0,<22.0.0)
Requires-Dist: chardet (>=4.0.0,<6.0.0)
Requires-Dist: cheroot (>=9.0.0,<10.0.0)
Requires-Dist: click (>=7.1.0,<9.0.0)
Requires-Dist: click-spinner (>=0.1.8,<0.2.0)
Requires-Dist: colorlog (>=4.1.0,<7.0.0)
Requires-Dist: dacite (>=1.0.2,<2.0.0)
Requires-Dist: datacommons (>=1.4.3,<2.0.0)
Requires-Dist: datacommons-pandas (>=0.0.3,<0.0.4)
Requires-Dist: dominate (>=2.4.0,<3.0.0)
Requires-Dist: dulwich (>=0.20.0,<0.22.0)
Requires-Dist: flit-core (>=3.1.0,<4.0.0) ; extra == "cloud"
Requires-Dist: folium (>=0.12.0,<0.15.0) ; extra == "plotting"
Requires-Dist: furl (>=2.0.0,<3.0.0)
Requires-Dist: glom (>=22.1.0,<24.0.0)
Requires-Dist: importlib_resources (>=3.0.0,<6.0.0)
Requires-Dist: ipynbname (>=2021.3.2)
Requires-Dist: jsonschema (>=3.2.0,<5.0.0)
Requires-Dist: lxml (>=4.0.0,<5.0.0)
Requires-Dist: matplotlib (>=3.2.0,<4.0.0) ; extra == "plotting"
Requires-Dist: micawber (>=0.5.0)
Requires-Dist: multimethod (>=1.9,<2.0)
Requires-Dist: nbconvert (>=5.6.1)
Requires-Dist: packaging (>=21.0.0,<24.0.0)
Requires-Dist: pandas (>=1.1.0,<2.0.0)
Requires-Dist: plotapi (>=6.0.0,<7.0.0) ; extra == "plotting"
Requires-Dist: plotly (>=5.0.0,<6.0.0) ; extra == "plotting"
Requires-Dist: posthog (>=1.4.0,<3.0.0)
Requires-Dist: pyarrow (>=6.0.0,<11.0.0)
Requires-Dist: pydantic (>=1.6.0,<2.0.0)
Requires-Dist: pyngrok (>=5.2.1,<6.0.0)
Requires-Dist: requests (>=2.19.0,<3.0.0)
Requires-Dist: requests-toolbelt (>=0.9.1,<2.0.0)
Requires-Dist: tabulate (>=0.8.9,<0.10.0)
Requires-Dist: toolz (>=0.11.0,<0.13.0)
Requires-Dist: typing-extensions (>=4.4.0,<5.0.0)
Requires-Dist: vega-datasets (>=0.9.0,<1.0.0)
Project-URL: Documentation, https://docs.datapane.com
Project-URL: Repository, https://github.com/datapane/datapane
